target_gcs/__init__.py
target_gcs/sinks.py
target_gcs/target.py
target_gcs/tests/__init__.py
target_gcs/tests/test_core.py
target_gcs/tests/test_sinks.py
target_gcs-1.2.3.dist-info/METADATA
target_gcs-1.2.3.dist-info/WHEEL
target_gcs-1.2.3.dist-info/entry_points.txt
target_gcs-1.2.3.dist-info/RECORD
