Metadata-Version: 2.4
Name: target-gcs
Version: 1.2.3
Summary: `target-gcs` is a Singer target for GCS, built with the Meltano SDK for Singer Targets.
License: Apache 2.0
Keywords: ELT,GCS
Author: Datateer Ops
Requires-Python: >=3.8,<4.0
Classifier: License :: Other/Proprietary License
Classifier: Programming Language :: Python :: 3
Classifier: Programming Language :: Python :: 3.8
Classifier: Programming Language :: Python :: 3.9
Classifier: Programming Language :: Python :: 3.10
Classifier: Programming Language :: Python :: 3.11
Classifier: Programming Language :: Python :: 3.12
Classifier: Programming Language :: Python :: 3.13
Classifier: Programming Language :: Python :: 3.14
Requires-Dist: google-api-python-client (>=2.49.0,<3.0.0)
Requires-Dist: google-cloud-storage (>=2.3.0,<3.0.0)
Requires-Dist: orjson (>=3.6.8,<4.0.0)
Requires-Dist: pytest-watch (>=4.2.0,<5.0.0)
Requires-Dist: requests (>=2.25.1,<3.0.0)
Requires-Dist: singer-sdk (>=0.40.0,<0.41.0)
Requires-Dist: smart-open[gcs] (>=6.0.0,<7.0.0)
